LICENSE
README.md
setup-3.py
setup.py
justpass_me_django.egg-info/PKG-INFO
justpass_me_django.egg-info/SOURCES.txt
justpass_me_django.egg-info/dependency_links.txt
justpass_me_django.egg-info/not-zip-safe
justpass_me_django.egg-info/requires.txt
justpass_me_django.egg-info/top_level.txt
justpassme/OIDC_CLIENT.py
justpassme/__init__.py
justpassme/admin.py
justpassme/apps.py
justpassme/helpers.py
justpassme/urls.py
justpassme/utils.py
justpassme/views.py