Metadata-Version: 2.1
Name: justpass-me-django
Version: 2.1.0
Summary: Django Integration with JustPass.me
Home-page: https://github.com/justpass-me/justpass-me-django
Author: JustPassMe
Author-email: sameh@justpass.me
License: MIT
Download-URL: https://github.com/justpass-me/justpass-me-django
Platform: UNKNOWN
Classifier: Development Status :: 5 - Production/Stable
Classifier: Environment :: Web Environment
Classifier: Framework :: Django
Classifier: Framework :: Django :: 2.0
Classifier: Framework :: Django :: 2.1
Classifier: Framework :: Django :: 2.2
Classifier: Intended Audience :: Developers
Classifier: Operating System :: OS Independent
Classifier: Programming Language :: Python
Classifier: Programming Language :: Python :: 3
Classifier: Programming Language :: Python :: 3.7
Classifier: Programming Language :: Python :: 3.8
Classifier: Topic :: Software Development :: Libraries :: Python Modules
Requires-Python: >=3.7
License-File: LICENSE
